[
    {
        "candidatePostulationDate": "2021-11-17 20:02",
        "candidateFullName": "Manuel Leoncio Espinoza Catachunga",
        "candidateAddress": "Av. Peru 4418, Callao, Lima, Peru",
        "len": 3,
        "addressCountry": "Peru",
        "addressDepartment": "Lima",
        "addressDistrict": "Callao",
        "address": "Av. Peru 4418"
    },
    {
        "candidatePostulationDate": "2021-11-13 19:15",
        "candidateFullName": "Robert Silva Campos",
        "candidateAddress": "Los Chasquis, Santa Anita, Municipalidad Metropolitana De Lima, Peru",
        "len": 3,
        "addressCountry": "Peru",
        "addressDepartment": "Municipalidad Metropolitana De Lima",
        "addressDistrict": "Santa Anita",
        "address": "Los Chasquis"
    },
    {
        "candidatePostulationDate": "2021-11-05 11:31",
        "candidateFullName": "Jeroboan Angel Garcia Llontop",
        "candidateAddress": "Claveles, Lima, Lima, Peru",
        "len": 3,
        "addressCountry": "Peru",
        "addressDepartment": "Lima",
        "addressDistrict": "Lima",
        "address": "Claveles"
    },
    {
        "candidatePostulationDate": "2021-11-03 23:37",
        "candidateFullName": "Marco Antonio Neciosup Panibra",
        "candidateAddress": "Avenida Central 11, Lima, Lima, Peru",
        "len": 3,
        "addressCountry": "Peru",
        "addressDepartment": "Lima",
        "addressDistrict": "Lima",
        "address": "Avenida Central 11"
    },
    {
        "candidatePostulationDate": "2021-11-03 09:44",
        "candidateFullName": "Oiver Tarrillo Vasquez",
        "candidateAddress": "Mz Tg Lt 8, Lurin, Lima, Peru",
        "len": 3,
        "addressCountry": "Peru",
        "addressDepartment": "Lima",
        "addressDistrict": "Lurin",
        "address": "Mz Tg Lt 8"
    },
    {
        "candidatePostulationDate": "2021-11-01 16:51",
        "candidateFullName": "Jorge Luis Martinez Cardenas",
        "candidateAddress": "Calle Los Negocios 280, Calle Los Negocios 280, Lima, Lima, Peru",
        "len": 4,
        "addressCountry": "Peru",
        "addressDepartment": "Lima",
        "addressDistrict": "Lima",
        "address": "Calle Los Negocios 280, Calle Los Negocios 280"
    },
    {
        "candidatePostulationDate": "2021-10-30 23:16",
        "candidateFullName": "Miguel Angel Villanueva Rengifo",
        "candidateAddress": "Av Gambeta, , Gobierno Regional Del Callao, Peru",
        "len": 3,
        "addressCountry": "Peru",
        "addressDepartment": "Gobierno Regional Del Callao",
        "addressDistrict": "",
        "address": "Av Gambeta"
    },
    {
        "candidatePostulationDate": "2021-10-30 14:06",
        "candidateFullName": "Percy Camala",
        "candidateAddress": "Av Argentina, Cusco, Cuzco, Peru",
        "len": 3,
        "addressCountry": "Peru",
        "addressDepartment": "Cuzco",
        "addressDistrict": "Cusco",
        "address": "Av Argentina"
    },
    {
        "candidatePostulationDate": "2021-10-28 15:51",
        "candidateFullName": "Jorge Manay Arevalo",
        "candidateAddress": "",
        "len": 0,
        "addressCountry": "",
        "addressDepartment": "",
        "addressDistrict": "",
        "address": ""
    },
    {
        "candidatePostulationDate": "2021-10-27 22:42",
        "candidateFullName": "Argenis Coromoto Junior Carvajal Perez",
        "candidateAddress": "321,17, Cercado De Lima, Lima, Peru",
        "len": 4,
        "addressCountry": "Peru",
        "addressDepartment": "Lima",
        "addressDistrict": "Cercado De Lima",
        "address": "321,17"
    }
]