[
    {
        "algoritmo": "DT",
        "tipo": "Particion 1",
        "registrosEntrenamiento": 6714,
        "registrosPrueba": 2237,
        "proporcionSobremuestreo": 0.2,
        "tiempoEjecucion": "1008ms",
        "matrizConfusion": "[[1760, 109], [47, 321]]",
        "exactitud": "93.03%",
        "precision": "74.65%",
        "sensibilidad": "87.23%",
        "valorF": "80.45%"
    },
    {
        "algoritmo": "DT",
        "tipo": "Particion 2",
        "registrosEntrenamiento": 6713,
        "registrosPrueba": 2238,
        "proporcionSobremuestreo": 0.2,
        "tiempoEjecucion": "774ms",
        "matrizConfusion": "[[1734, 103], [31, 370]]",
        "exactitud": "94.01%",
        "precision": "78.22%",
        "sensibilidad": "92.27%",
        "valorF": "84.67%"
    },
    {
        "algoritmo": "DT",
        "tipo": "Particion 3",
        "registrosEntrenamiento": 6713,
        "registrosPrueba": 2238,
        "proporcionSobremuestreo": 0.2,
        "tiempoEjecucion": "818ms",
        "matrizConfusion": "[[1761, 99], [45, 333]]",
        "exactitud": "93.57%",
        "precision": "77.08%",
        "sensibilidad": "88.10%",
        "valorF": "82.22%"
    },
    {
        "algoritmo": "DT",
        "tipo": "Particion 4",
        "registrosEntrenamiento": 6713,
        "registrosPrueba": 2238,
        "proporcionSobremuestreo": 0.2,
        "tiempoEjecucion": "854ms",
        "matrizConfusion": "[[1770, 106], [42, 320]]",
        "exactitud": "93.39%",
        "precision": "75.12%",
        "sensibilidad": "88.40%",
        "valorF": "81.22%"
    },
    {
        "algoritmo": "DT",
        "tipo": "Total de datos",
        "registrosEntrenamiento": 8951,
        "registrosPrueba": 2984,
        "proporcionSobremuestreo": 0.2,
        "tiempoEjecucion": "1155ms",
        "matrizConfusion": "[[2394, 110], [43, 437]]",
        "exactitud": "94.87%",
        "precision": "79.89%",
        "sensibilidad": "91.04%",
        "valorF": "85.10%"
    },
    {
        "algoritmo": "GB",
        "tipo": "Particion 1",
        "registrosEntrenamiento": 6714,
        "registrosPrueba": 2237,
        "proporcionSobremuestreo": 0.2,
        "tiempoEjecucion": "3828ms",
        "matrizConfusion": "[[1864, 5], [302, 66]]",
        "exactitud": "86.28%",
        "precision": "92.96%",
        "sensibilidad": "17.93%",
        "valorF": "30.07%"
    },
    {
        "algoritmo": "GB",
        "tipo": "Particion 2",
        "registrosEntrenamiento": 6713,
        "registrosPrueba": 2238,
        "proporcionSobremuestreo": 0.2,
        "tiempoEjecucion": "3795ms",
        "matrizConfusion": "[[1832, 5], [313, 88]]",
        "exactitud": "85.79%",
        "precision": "94.62%",
        "sensibilidad": "21.95%",
        "valorF": "35.63%"
    },
    {
        "algoritmo": "GB",
        "tipo": "Particion 3",
        "registrosEntrenamiento": 6713,
        "registrosPrueba": 2238,
        "proporcionSobremuestreo": 0.2,
        "tiempoEjecucion": "3985ms",
        "matrizConfusion": "[[1857, 3], [300, 78]]",
        "exactitud": "86.46%",
        "precision": "96.30%",
        "sensibilidad": "20.63%",
        "valorF": "33.99%"
    },
    {
        "algoritmo": "GB",
        "tipo": "Particion 4",
        "registrosEntrenamiento": 6713,
        "registrosPrueba": 2238,
        "proporcionSobremuestreo": 0.2,
        "tiempoEjecucion": "5083ms",
        "matrizConfusion": "[[1874, 2], [283, 79]]",
        "exactitud": "87.27%",
        "precision": "97.53%",
        "sensibilidad": "21.82%",
        "valorF": "35.67%"
    },
    {
        "algoritmo": "GB",
        "tipo": "Total de datos",
        "registrosEntrenamiento": 8951,
        "registrosPrueba": 2984,
        "proporcionSobremuestreo": 0.2,
        "tiempoEjecucion": "5341ms",
        "matrizConfusion": "[[2499, 5], [378, 102]]",
        "exactitud": "87.16%",
        "precision": "95.33%",
        "sensibilidad": "21.25%",
        "valorF": "34.75%"
    },
    {
        "algoritmo": "GNB",
        "tipo": "Particion 1",
        "registrosEntrenamiento": 6714,
        "registrosPrueba": 2237,
        "proporcionSobremuestreo": 0.2,
        "tiempoEjecucion": "133ms",
        "matrizConfusion": "[[570, 1299], [12, 356]]",
        "exactitud": "41.39%",
        "precision": "21.51%",
        "sensibilidad": "96.74%",
        "valorF": "35.20%"
    },
    {
        "algoritmo": "GNB",
        "tipo": "Particion 2",
        "registrosEntrenamiento": 6713,
        "registrosPrueba": 2238,
        "proporcionSobremuestreo": 0.2,
        "tiempoEjecucion": "97ms",
        "matrizConfusion": "[[531, 1306], [11, 390]]",
        "exactitud": "41.15%",
        "precision": "23.00%",
        "sensibilidad": "97.26%",
        "valorF": "37.20%"
    },
    {
        "algoritmo": "GNB",
        "tipo": "Particion 3",
        "registrosEntrenamiento": 6713,
        "registrosPrueba": 2238,
        "proporcionSobremuestreo": 0.2,
        "tiempoEjecucion": "109ms",
        "matrizConfusion": "[[596, 1264], [16, 362]]",
        "exactitud": "42.81%",
        "precision": "22.26%",
        "sensibilidad": "95.77%",
        "valorF": "36.13%"
    },
    {
        "algoritmo": "GNB",
        "tipo": "Particion 4",
        "registrosEntrenamiento": 6713,
        "registrosPrueba": 2238,
        "proporcionSobremuestreo": 0.2,
        "tiempoEjecucion": "97ms",
        "matrizConfusion": "[[571, 1305], [23, 339]]",
        "exactitud": "40.66%",
        "precision": "20.62%",
        "sensibilidad": "93.65%",
        "valorF": "33.80%"
    },
    {
        "algoritmo": "GNB",
        "tipo": "Total de datos",
        "registrosEntrenamiento": 8951,
        "registrosPrueba": 2984,
        "proporcionSobremuestreo": 0.2,
        "tiempoEjecucion": "138ms",
        "matrizConfusion": "[[701, 1803], [12, 468]]",
        "exactitud": "39.18%",
        "precision": "20.61%",
        "sensibilidad": "97.50%",
        "valorF": "34.02%"
    },
    {
        "algoritmo": "KNN",
        "tipo": "Particion 1",
        "registrosEntrenamiento": 6714,
        "registrosPrueba": 2237,
        "proporcionSobremuestreo": 0.2,
        "tiempoEjecucion": "194ms",
        "matrizConfusion": "[[1743, 126], [142, 226]]",
        "exactitud": "88.02%",
        "precision": "64.20%",
        "sensibilidad": "61.41%",
        "valorF": "62.78%"
    },
    {
        "algoritmo": "KNN",
        "tipo": "Particion 2",
        "registrosEntrenamiento": 6713,
        "registrosPrueba": 2238,
        "proporcionSobremuestreo": 0.2,
        "tiempoEjecucion": "171ms",
        "matrizConfusion": "[[1725, 112], [159, 242]]",
        "exactitud": "87.89%",
        "precision": "68.36%",
        "sensibilidad": "60.35%",
        "valorF": "64.11%"
    },
    {
        "algoritmo": "KNN",
        "tipo": "Particion 3",
        "registrosEntrenamiento": 6713,
        "registrosPrueba": 2238,
        "proporcionSobremuestreo": 0.2,
        "tiempoEjecucion": "176ms",
        "matrizConfusion": "[[1741, 119], [154, 224]]",
        "exactitud": "87.80%",
        "precision": "65.31%",
        "sensibilidad": "59.26%",
        "valorF": "62.14%"
    },
    {
        "algoritmo": "KNN",
        "tipo": "Particion 4",
        "registrosEntrenamiento": 6713,
        "registrosPrueba": 2238,
        "proporcionSobremuestreo": 0.2,
        "tiempoEjecucion": "176ms",
        "matrizConfusion": "[[1726, 150], [153, 209]]",
        "exactitud": "86.46%",
        "precision": "58.22%",
        "sensibilidad": "57.73%",
        "valorF": "57.98%"
    },
    {
        "algoritmo": "KNN",
        "tipo": "Total de datos",
        "registrosEntrenamiento": 8951,
        "registrosPrueba": 2984,
        "proporcionSobremuestreo": 0.2,
        "tiempoEjecucion": "347ms",
        "matrizConfusion": "[[2346, 158], [150, 330]]",
        "exactitud": "89.68%",
        "precision": "67.62%",
        "sensibilidad": "68.75%",
        "valorF": "68.18%"
    },
    {
        "algoritmo": "LR",
        "tipo": "Particion 1",
        "registrosEntrenamiento": 6714,
        "registrosPrueba": 2237,
        "proporcionSobremuestreo": 0.2,
        "tiempoEjecucion": "415ms",
        "matrizConfusion": "[[1806, 63], [276, 92]]",
        "exactitud": "84.85%",
        "precision": "59.35%",
        "sensibilidad": "25.00%",
        "valorF": "35.18%"
    },
    {
        "algoritmo": "LR",
        "tipo": "Particion 2",
        "registrosEntrenamiento": 6713,
        "registrosPrueba": 2238,
        "proporcionSobremuestreo": 0.2,
        "tiempoEjecucion": "297ms",
        "matrizConfusion": "[[1810, 27], [277, 124]]",
        "exactitud": "86.42%",
        "precision": "82.12%",
        "sensibilidad": "30.92%",
        "valorF": "44.93%"
    },
    {
        "algoritmo": "LR",
        "tipo": "Particion 3",
        "registrosEntrenamiento": 6713,
        "registrosPrueba": 2238,
        "proporcionSobremuestreo": 0.2,
        "tiempoEjecucion": "297ms",
        "matrizConfusion": "[[1822, 38], [259, 119]]",
        "exactitud": "86.73%",
        "precision": "75.80%",
        "sensibilidad": "31.48%",
        "valorF": "44.49%"
    },
    {
        "algoritmo": "LR",
        "tipo": "Particion 4",
        "registrosEntrenamiento": 6713,
        "registrosPrueba": 2238,
        "proporcionSobremuestreo": 0.2,
        "tiempoEjecucion": "324ms",
        "matrizConfusion": "[[1832, 44], [243, 119]]",
        "exactitud": "87.18%",
        "precision": "73.01%",
        "sensibilidad": "32.87%",
        "valorF": "45.33%"
    },
    {
        "algoritmo": "LR",
        "tipo": "Total de datos",
        "registrosEntrenamiento": 8951,
        "registrosPrueba": 2984,
        "proporcionSobremuestreo": 0.2,
        "tiempoEjecucion": "495ms",
        "matrizConfusion": "[[2453, 51], [330, 150]]",
        "exactitud": "87.23%",
        "precision": "74.63%",
        "sensibilidad": "31.25%",
        "valorF": "44.05%"
    },
    {
        "algoritmo": "RF",
        "tipo": "Particion 1",
        "registrosEntrenamiento": 6714,
        "registrosPrueba": 2237,
        "proporcionSobremuestreo": 0.2,
        "tiempoEjecucion": "2228ms",
        "matrizConfusion": "[[1869, 0], [49, 319]]",
        "exactitud": "97.81%",
        "precision": "100.00%",
        "sensibilidad": "86.68%",
        "valorF": "92.87%"
    },
    {
        "algoritmo": "RF",
        "tipo": "Particion 2",
        "registrosEntrenamiento": 6713,
        "registrosPrueba": 2238,
        "proporcionSobremuestreo": 0.2,
        "tiempoEjecucion": "2283ms",
        "matrizConfusion": "[[1837, 0], [31, 370]]",
        "exactitud": "98.61%",
        "precision": "100.00%",
        "sensibilidad": "92.27%",
        "valorF": "95.98%"
    },
    {
        "algoritmo": "RF",
        "tipo": "Particion 3",
        "registrosEntrenamiento": 6713,
        "registrosPrueba": 2238,
        "proporcionSobremuestreo": 0.2,
        "tiempoEjecucion": "2339ms",
        "matrizConfusion": "[[1860, 0], [51, 327]]",
        "exactitud": "97.72%",
        "precision": "100.00%",
        "sensibilidad": "86.51%",
        "valorF": "92.77%"
    },
    {
        "algoritmo": "RF",
        "tipo": "Particion 4",
        "registrosEntrenamiento": 6713,
        "registrosPrueba": 2238,
        "proporcionSobremuestreo": 0.2,
        "tiempoEjecucion": "2492ms",
        "matrizConfusion": "[[1875, 1], [45, 317]]",
        "exactitud": "97.94%",
        "precision": "99.69%",
        "sensibilidad": "87.57%",
        "valorF": "93.24%"
    },
    {
        "algoritmo": "RF",
        "tipo": "Total de datos",
        "registrosEntrenamiento": 8951,
        "registrosPrueba": 2984,
        "proporcionSobremuestreo": 0.2,
        "tiempoEjecucion": "2916ms",
        "matrizConfusion": "[[2504, 0], [45, 435]]",
        "exactitud": "98.49%",
        "precision": "100.00%",
        "sensibilidad": "90.62%",
        "valorF": "95.08%"
    },
    {
        "algoritmo": "SVM",
        "tipo": "Particion 1",
        "registrosEntrenamiento": 6714,
        "registrosPrueba": 2237,
        "proporcionSobremuestreo": 0.2,
        "tiempoEjecucion": "9336ms",
        "matrizConfusion": "[[1869, 0], [268, 100]]",
        "exactitud": "88.02%",
        "precision": "100.00%",
        "sensibilidad": "27.17%",
        "valorF": "42.74%"
    },
    {
        "algoritmo": "SVM",
        "tipo": "Particion 2",
        "registrosEntrenamiento": 6713,
        "registrosPrueba": 2238,
        "proporcionSobremuestreo": 0.2,
        "tiempoEjecucion": "7851ms",
        "matrizConfusion": "[[1837, 0], [280, 121]]",
        "exactitud": "87.49%",
        "precision": "100.00%",
        "sensibilidad": "30.17%",
        "valorF": "46.36%"
    },
    {
        "algoritmo": "SVM",
        "tipo": "Particion 3",
        "registrosEntrenamiento": 6713,
        "registrosPrueba": 2238,
        "proporcionSobremuestreo": 0.2,
        "tiempoEjecucion": "9807ms",
        "matrizConfusion": "[[1860, 0], [264, 114]]",
        "exactitud": "88.20%",
        "precision": "100.00%",
        "sensibilidad": "30.16%",
        "valorF": "46.34%"
    },
    {
        "algoritmo": "SVM",
        "tipo": "Particion 4",
        "registrosEntrenamiento": 6713,
        "registrosPrueba": 2238,
        "proporcionSobremuestreo": 0.2,
        "tiempoEjecucion": "11560ms",
        "matrizConfusion": "[[1876, 0], [239, 123]]",
        "exactitud": "89.32%",
        "precision": "100.00%",
        "sensibilidad": "33.98%",
        "valorF": "50.72%"
    },
    {
        "algoritmo": "SVM",
        "tipo": "Total de datos",
        "registrosEntrenamiento": 8951,
        "registrosPrueba": 2984,
        "proporcionSobremuestreo": 0.2,
        "tiempoEjecucion": "16548ms",
        "matrizConfusion": "[[2504, 0], [285, 195]]",
        "exactitud": "90.45%",
        "precision": "100.00%",
        "sensibilidad": "40.62%",
        "valorF": "57.78%"
    }
]